{
  "id": "8604b1c6960a",
  "nome": "Teste",
  "email": "teste@teste.com",
  "senha_hash": "8d969eef6ecad3c29a3a629280e686cf0c3f5d5a86aff3ca12020c923adc6c92",
  "idade": 25,
  "peso": 70,
  "altura": 170,
  "sexo": "M",
  "objetivo_principal": "hipertrofia",
  "objetivos_secundarios": [],
  "nivel": "iniciante",
  "tempo_treino_meses": 0,
  "dias_disponiveis": 4,
  "tempo_por_treino_minutos": 60,
  "horario_preferido": "noite",
  "limitacoes": [],
  "condicoes_medicas": [],
  "equipamentos": [
    "barra",
    "halteres",
    "maquinas",
    "cabos"
  ],
  "treina_em": "academia",
  "exercicios_favoritos": [],
  "exercicios_evitar": [],
  "prefere_compostos": true,
  "historico_interacoes": [],
  "historico_treinos": [],
  "progressos": [],
  "treino_atual": null,
  "perfil_completo": false,
  "criado_em": "2026-01-17T00:38:02.853240",
  "atualizado_em": "2026-01-17T00:38:02.853244"
}